iamt/__init__.py
iamt/__main__.py
iamt/client_config/client_config.py
iamt/completers/customCompleter.py
iamt/composes/5425CICD/gitea/.rdm.md
iamt/composes/5425CICD/gitea/docker-compose.yml
iamt/composes/5425CICD/gitlab/.rdm.md
iamt/composes/5425CICD/gitlab/config/ssl/.gitkeep
iamt/composes/5425CICD/gitlab/docker-compose.yml
iamt/composes/5425CICD/gitlabDocs/.rdm.md
iamt/composes/5425CICD/gitlabRunner/.rdm.md
iamt/composes/5425CICD/sonarQube/.rdm.md
iamt/composes/5425CICD/sonarQube/docker-compose.yml
iamt/composes/5425CICD/sonarQube/docker-compose3.yml
iamt/composes/5425CICD/sonarQube/docker-compose4.yml
iamt/composes/5425CICD/sonarQube/sonarqube_conf/.gitkeep
iamt/composes/5425CICD/sonarQube/sonarqube_data/.gitkeep
iamt/composes/5425CICD/sonarQube/sonarqube_extensions/.gitkeep
iamt/composes/5425CICD/sonarQube/sonarqube_logs/.gitkeep
iamt/composes/5425CICD/sonarQube/sonarqube_temp/.gitkeep
iamt/composes/5435PROMPT/.rdm.md
iamt/composes/5435PROMPT/langfuse/.env
iamt/composes/5435PROMPT/langfuse/.rdm.md
iamt/composes/5435PROMPT/langfuse/docker-compose.yml
iamt/composes/5435PROMPT/prompt-optimizer/.rdm.md
iamt/composes/5465BASE/alpine/.rdm.md
iamt/composes/5465BASE/mysql/.rdm.md
iamt/composes/5465BASE/mysql/conf/my.cnf
iamt/composes/5465BASE/mysql/docker-compose.yml
iamt/composes/5465BASE/mysql/init/01-init.sql
iamt/composes/5465BASE/nginx/.rdm.md
iamt/composes/5465BASE/nginx/docker-compose.yml
iamt/composes/5465BASE/nginx/html/index.html
iamt/composes/5465BASE/nginx/nginx/conf.d/default.conf
iamt/composes/5465BASE/nginx/nginx/nginx.conf
iamt/composes/5465BASE/node/.rdm.md
iamt/composes/5465BASE/node/docker-compose.yml
iamt/composes/5465BASE/php/.rdm.md
iamt/composes/5465BASE/php/docker-compose.yml
iamt/composes/5465BASE/redis/.env
iamt/composes/5465BASE/redis/.rdm.md
iamt/composes/5465BASE/redis/config/redis.conf
iamt/composes/5465BASE/redis/docker-compose.yml
iamt/composes/5475TTS/GPTsovits/.rdm.md
iamt/composes/5475TTS/GPTsovits/docker-compose.yml
iamt-1.1.46.dist-info/WHEEL
iamt-1.1.46.dist-info/entry_points.txt
iamt-1.1.46.dist-info/METADATA
iamt-1.1.46.dist-info/RECORD
