Metadata-Version: 2.3
Name: iamt
Version: 1.1.46
Summary: 这是一个灵活的自动化运维工具
Author: lipanpan
Author-email: lipanpan <lipanpanmail@163.com>
Requires-Dist: fabric>=3.2.2
Requires-Dist: fire>=0.7.1
Requires-Dist: gitpython>=3.1.46
Requires-Dist: jinja2>=3.1.6
Requires-Dist: prompt-toolkit>=3.0.52
Requires-Dist: pyperclip>=1.11.0
Requires-Dist: pyyaml>=6.0.3
Requires-Dist: questionary>=2.1.1
Requires-Dist: rich>=14.2.0
Requires-Dist: toml>=0.10.2
Requires-Python: ~=3.13.0
